stark/__init__.py
stark/stark.py
stark/utilities.py
stark_denoise-0.1.0.dist-info/licenses/LICENSE
stark_denoise-0.1.0.dist-info/METADATA
stark_denoise-0.1.0.dist-info/WHEEL
stark_denoise-0.1.0.dist-info/top_level.txt
stark_denoise-0.1.0.dist-info/RECORD
