Metadata-Version: 2.4
Name: stark-denoise
Version: 0.1.0
Summary: A Python package for denoising spatial transcriptomics data.
Author-email: Sharvaj Kubal <kubalsharvaj@gmail.com>
License-Expression: MIT
Project-URL: Source Code, https://github.com/schiebingerlab/STARK
Classifier: Programming Language :: Python :: 3
Classifier: Operating System :: OS Independent
Classifier: Topic :: Scientific/Engineering :: Bio-Informatics
Requires-Python: >=3.8
License-File: LICENSE
Requires-Dist: numpy
Requires-Dist: scipy
Requires-Dist: pandas
Requires-Dist: anndata
Requires-Dist: scanpy
Requires-Dist: scikit-learn
Requires-Dist: seaborn
Requires-Dist: matplotlib
Dynamic: license-file
